[{
  "SourceFile": "raw-images/003/IMG_2585.jpg",
  "ExifToolVersion": 12.76,
  "FileName": "IMG_2585.jpg",
  "Directory": "raw-images/003",
  "FileSize": "2.2 MB",
  "FileModifyDate": "2026:01:06 11:31:34+00:00",
  "FileAccessDate": "2026:01:10 09:10:01+00:00",
  "FileInodeChangeDate": "2026:01:10 09:08:52+00:00",
  "FilePermissions": "-rw-r--r--",
  "FileType": "JPEG",
  "FileTypeExtension": "jpg",
  "MIMEType": "image/jpeg",
  "JFIFVersion": 1.01,
  "ResolutionUnit": "inches",
  "XResolution": 72,
  "YResolution": 72,
  "ImageWidth": 3311,
  "ImageHeight": 1862,
  "EncodingProcess": "Baseline DCT, Huffman coding",
  "BitsPerSample": 8,
  "ColorComponents": 3,
  "YCbCrSubSampling": "YCbCr4:4:4 (1 1)",
  "ImageSize": "3311x1862",
  "Megapixels": 6.2
}]
